openrlbenchmark/__init__.py
openrlbenchmark/cache.py
openrlbenchmark/cache_legacy.py
openrlbenchmark/capped_hns.py
openrlbenchmark/hns.py
openrlbenchmark/offline_db.py
openrlbenchmark/rlops copy.py
openrlbenchmark/rlops.py
openrlbenchmark/rlops_hns.py
openrlbenchmark_nightly-0.2.0b3.dist-info/LICENSE
openrlbenchmark_nightly-0.2.0b3.dist-info/METADATA
openrlbenchmark_nightly-0.2.0b3.dist-info/WHEEL
openrlbenchmark_nightly-0.2.0b3.dist-info/RECORD
