Metadata-Version: 2.1
Name: openrlbenchmark-nightly
Version: 0.2.0b3
Summary: 
Author: Costa Huang
Author-email: costa.huang@outlook.com
Requires-Python: >=3.7.1,<3.11
Classifier: Programming Language :: Python :: 3
Classifier: Programming Language :: Python :: 3.8
Classifier: Programming Language :: Python :: 3.9
Classifier: Programming Language :: Python :: 3.10
Requires-Dist: dotmap (>=1.3.30,<2.0.0)
Requires-Dist: expt (>=0.4.1,<0.5.0)
Requires-Dist: importlib-metadata (>=5.1.0,<6.0.0)
Requires-Dist: multiprocess (>=0.70.13,<0.71.0)
Requires-Dist: peewee (>=3.16.2,<4.0.0)
Requires-Dist: pip (>=22.1.2,<23.0.0)
Requires-Dist: rich (<12.0)
Requires-Dist: rliable (>=1.0.8,<2.0.0)
Requires-Dist: seaborn (>=0.12.1,<0.13.0)
Requires-Dist: tabulate (>=0.9.0,<0.10.0)
Requires-Dist: tqdm (>=4.65.0,<5.0.0)
Requires-Dist: tueplots (>=0.0.4,<0.0.5)
Requires-Dist: tyro (>=0.5.0,<0.6.0)
Requires-Dist: wandb (>=0.13.7,<0.14.0)
